aibaba_ai_core/__init__.py
aibaba_ai_core/_api/__init__.py
aibaba_ai_core/_api/beta_decorator.py
aibaba_ai_core/_api/deprecation.py
aibaba_ai_core/_api/internal.py
aibaba_ai_core/_api/path.py
aibaba_ai_core/agents.py
aibaba_ai_core/beta/__init__.py
aibaba_ai_core/beta/runnables/__init__.py
aibaba_ai_core/beta/runnables/context.py
aibaba_ai_core/caches.py
aibaba_ai_core/callbacks/__init__.py
aibaba_ai_core/callbacks/base.py
aibaba_ai_core/callbacks/file.py
aibaba_ai_core/callbacks/manager.py
aibaba_ai_core/callbacks/stdout.py
aibaba_ai_core/callbacks/streaming_stdout.py
aibaba_ai_core/chat_history.py
aibaba_ai_core/chat_loaders.py
aibaba_ai_core/chat_sessions.py
aibaba_ai_core/document_loaders/__init__.py
aibaba_ai_core/document_loaders/base.py
aibaba_ai_core/document_loaders/blob_loaders.py
aibaba_ai_core/document_loaders/langsmith.py
aibaba_ai_core/documents/__init__.py
aibaba_ai_core/documents/base.py
aibaba_ai_core/documents/compressor.py
aibaba_ai_core/documents/transformers.py
aibaba_ai_core/embeddings/__init__.py
aibaba_ai_core/embeddings/embeddings.py
aibaba_ai_core/embeddings/fake.py
aibaba_ai_core/env.py
aibaba_ai_core/example_selectors/__init__.py
aibaba_ai_core/example_selectors/base.py
aibaba_ai_core/example_selectors/length_based.py
aibaba_ai_core/example_selectors/semantic_similarity.py
aibaba_ai_core/exceptions.py
aibaba_ai_core/globals.py
aibaba_ai_core/indexing/__init__.py
aibaba_ai_core/indexing/api.py
aibaba_ai_core/indexing/base.py
aibaba_ai_core/indexing/in_memory.py
aibaba_ai_core/language_models/__init__.py
aibaba_ai_core/language_models/base.py
aibaba_ai_core/language_models/chat_models.py
aibaba_ai_core/language_models/fake.py
aibaba_ai_core/language_models/fake_chat_models.py
aibaba_ai_core/language_models/llms.py
aibaba_ai_core/load/__init__.py
aibaba_ai_core/load/dump.py
aibaba_ai_core/load/load.py
aibaba_ai_core/load/mapping.py
aibaba_ai_core/load/serializable.py
aibaba_ai_core/memory.py
aibaba_ai_core/messages/__init__.py
aibaba_ai_core-0.3.33.dist-info/METADATA
aibaba_ai_core-0.3.33.dist-info/WHEEL
aibaba_ai_core-0.3.33.dist-info/RECORD
