Metadata-Version: 2.3
Name: aibaba_ai_core
Version: 0.3.33
Summary: Aibaba AI Core library for building AI Agents
License: MIT
Requires-Python: >=3.9,<4.0
Classifier: License :: OSI Approved :: MIT License
Classifier: Programming Language :: Python :: 3
Classifier: Programming Language :: Python :: 3.9
Classifier: Programming Language :: Python :: 3.10
Classifier: Programming Language :: Python :: 3.11
Classifier: Programming Language :: Python :: 3.12
Classifier: Programming Language :: Python :: 3.13
Requires-Dist: PyYAML (>=5.3)
Requires-Dist: jsonpatch (>=1.33,<2.0)
Requires-Dist: langsmith (>=0.1.125,<0.3)
Requires-Dist: packaging (>=23.2,<25)
Requires-Dist: pydantic (>=2.5.2,<3.0.0) ; python_full_version < "3.12.4"
Requires-Dist: pydantic (>=2.7.4,<3.0.0) ; python_full_version >= "3.12.4"
Requires-Dist: tenacity (>=8.1.0,!=8.4.0,<10.0.0)
Requires-Dist: typing-extensions (>=4.7)
Project-URL: Repository, https://github.com/aibaba-ai/aibaba-ai
Project-URL: Release Notes, https://github.com/aibaba-ai/aibaba-ai/releases?q=tag%3A%22langchain-core%3D%3D0%22&expanded=true
Project-URL: Source Code, https://github.com/aibaba-ai/aibaba-ai/tree/master/libs/core
